LICENSE.md
MANIFEST.in
README.md
example.png
setup.cfg
setup.py
django_vue_tabs/__init__.py
django_vue_tabs/admin.py
django_vue_tabs/settings.py
django_vue_tabs.egg-info/PKG-INFO
django_vue_tabs.egg-info/SOURCES.txt
django_vue_tabs.egg-info/dependency_links.txt
django_vue_tabs.egg-info/not-zip-safe
django_vue_tabs.egg-info/top_level.txt
django_vue_tabs/static/django_vue_tabs/tabs.js
django_vue_tabs/static/django_vue_tabs/vue-2.6.11.min.js
django_vue_tabs/static/django_vue_tabs/vue-tabs-component-1.5.3.css
django_vue_tabs/static/django_vue_tabs/vue-tabs-component-1.5.3.js
django_vue_tabs/templates/django_vue_tabs/change_form.html