Metadata-Version: 1.1
Name: django-vue-tabs
Version: 0.0.13
Summary: Django: Add tabs to ModelAdmin 
Home-page: http://github.com/microdisseny/django-vue-tabs
Author: MICRODISSENY GISCUBE SL
Author-email: tech@microdisseny.com
License: MIT License
Platform: OS Independent
Classifier: Framework :: Django
Classifier: Intended Audience :: Developers
Classifier: License :: OSI Approved :: MIT License
Classifier: Operating System :: OS Independent
Classifier: Topic :: Software Development
Classifier: Programming Language :: Python :: 3
Classifier: Environment :: Web Environment
Classifier: Development Status :: 5 - Production/Stable
Classifier: Topic :: Software Development :: Libraries :: Python Modules
